loupedeck_python/__init__.py
loupedeck_python/color.py
loupedeck_python/connections/__init__.py
loupedeck_python/connections/base.py
loupedeck_python/connections/serial.py
loupedeck_python/connections/ws.py
loupedeck_python/constants.py
loupedeck_python/device.py
loupedeck_python/discovery.py
loupedeck_python/events.py
loupedeck_python/parser.py
loupedeck_python/py.typed
loupedeck_python/types.py
loupedeck_python/util.py
loupedeck_python-0.1.2.dist-info/licenses/LICENSE
loupedeck_python-0.1.2.dist-info/WHEEL
loupedeck_python-0.1.2.dist-info/METADATA
loupedeck_python-0.1.2.dist-info/RECORD
