Metadata-Version: 2.4
Name: loupedeck-python
Version: 0.1.2
Summary: Async Python port of the Loupedeck Node.js library for Live, Live S, CT, and Razer Stream Controller devices.
Keywords: loupedeck,razer,stream-controller,hardware,usb,hid
Author: Marian Hahne
Author-email: Marian Hahne <marian@marianhahne.de>
License-Expression: MIT
License-File: LICENSE
Requires-Dist: pillow>=12.0.0
Requires-Dist: psutil>=7.2.0
Requires-Dist: pyserial>=3.5
Requires-Dist: pyserial-asyncio>=0.6
Requires-Dist: websockets>=15.0.1
Requires-Python: >=3.14
Project-URL: Repository, https://codeberg.org/rotespferd/loupedeck-python
